<?xml version="1.0" encoding="utf-8"?>
<JavaClass xmlns:xsi="http://www.w3.org/2001/XMLSchema-instance" xmlns:xsd="http://www.w3.org/2001/XMLSchema">
  <Name>BlockChest</Name>
  <Action>Ignore</Action>
  <DefaultMethodAction>Compile</DefaultMethodAction>
  <Methods>
    <MethodDetail>
      <Name>breakBlock</Name>
      <Comments>We won't handle a chest breaking in our scope, will be treated like a normal block breaking.</Comments>
      <Action>Exclude</Action>
      <DependantOn />
    </MethodDetail>
    <MethodDetail>
      <Name>onBlockActivated</Name>
      <Comments>Not doing chest functionality at this time.</Comments>
      <Action>Exclude</Action>
      <DependantOn />
    </MethodDetail>
    <MethodDetail>
      <Name>func_94442_h_</Name>
      <Comments>Not doing chest functionality at this time.</Comments>
      <Action>Exclude</Action>
      <DependantOn />
    </MethodDetail>
    <MethodDetail>
      <Name>func_94328_b_</Name>
      <Comments>Not being used as far as I can tell.</Comments>
      <Action>Exclude</Action>
      <DependantOn />
    </MethodDetail>
    <MethodDetail>
      <Name>isOcelotBlockingChest</Name>
      <Comments>Not within scope.</Comments>
      <Action>Exclude</Action>
      <DependantOn />
    </MethodDetail>
  </Methods>
  <Fields />
</JavaClass>