<?xml version="1.0" encoding="utf-8"?>
<JavaClass xmlns:xsi="http://www.w3.org/2001/XMLSchema-instance" xmlns:xsd="http://www.w3.org/2001/XMLSchema">
  <Name>BlockComparator</Name>
  <Action>Compile</Action>
  <DefaultMethodAction>Compile</DefaultMethodAction>
  <Methods>
    <MethodDetail>
      <Name>onBlockActivated</Name>
      <Comments>Needs manual conversion to handle bitwise operations on bools.</Comments>
      <Action>Extend</Action>
      <DependantOn>
        <string>func_96476_c</string>
      </DependantOn>
    </MethodDetail>
  </Methods>
  <Fields />
</JavaClass>